download_gitignore/__init__.py
download_gitignore/download_gitignore.py
download_gitignore/github_api.py
download_gitignore-2.0.1.dist-info/LICENSE
download_gitignore-2.0.1.dist-info/METADATA
download_gitignore-2.0.1.dist-info/WHEEL
download_gitignore-2.0.1.dist-info/entry_points.txt
download_gitignore-2.0.1.dist-info/top_level.txt
download_gitignore-2.0.1.dist-info/RECORD
