Metadata-Version: 2.1
Name: download-gitignore
Version: 2.0.1
Summary: A Python CLI program to download .gitignore files from Github's repository
Home-page: https://github.com/vccolombo/download-gitignore
Author: Víctor Cora Colombo
License: UNKNOWN
Platform: UNKNOWN
Classifier: Development Status :: 5 - Production/Stable
Classifier: Environment :: Console
Classifier: Programming Language :: Python :: 3
Classifier: License :: OSI Approved :: MIT License
Classifier: Topic :: Software Development :: Version Control :: Git
Requires-Python: >=3.5
Requires-Dist: click (==7.0)
Requires-Dist: requests (==2.22.0)
